{"paths":{},"types":[],"uuids":["29FYIk+N1GYaeWH/q1NxQO","a2MjXRFdtLlYQ5ouAFv/+R","e97GVMl6JHh5Ml5qEDdSGa","f0BIwQ8D5Ml7nTNQbh1YlS","01mbnMDZpKp7WiOce54zJE","019EnMmI9OzppcG9cLGVww","02sG02nYJBAYEs0TUeDLi+","08YGmGMSBNzJ08UHQWGgqI","0bNXjxKWdE5aBd6YrooL/N","0c7/txfa1BH6rd+KF5KzO0","17Z0Bf0gJJlI3/K/KzgLGp","1caU8ymWVK6Z5e3KfWF1h2","29WhM4QgZKjq3Rm3RHCYLi","2aaEweOYxO/rK+I4ydrlMx","3aJKpV1JdFSpzzW9DXy8M2","41oiUCceJO45rB810/mZOu","4bVqXd0INDUboBWVAJW4Vt","4eEZRYdXtEZaZhZ3zfcYe1","5bsNXmEj9Gq4ZdQliDLiXQ","65jyA5vZRGvq8rkqeHENlR","66CFY3dc9NMLyByYALht7b","71VhFCTINJM6/Ky3oX9nBT","7d/m/IPz1F6oewD+J+Rr25","80TgMKsV5FW4kpz4FAz4Um","806GO4bOVPZpZ6/Ms9UMMM","82KEp2RR1H27qwxnIN+Hw0","84GJwWhyhEupUET31pBcOP","96yXUn3OdFmoMh3Er/4R0c","99FwsL0hBG8bITfZ4/IwmK","9aYlXtOnBOyYh1sV6G62a2","a1vEYGKQdDhLEeIqGzz1iE","a4+UsPCJtOLqGjV/v5buS3","aaoViR/q5HuaphaWu9W+Pj","b0vCGyjlJMaLAPtrJyTzdf","b4P/PCArtIdIH38t6mlw8Y","c4pD5eSglG4ZVyAOkDj2kS","c6/bTeyV1KrK+sWQb3vITq","c83MWMpdhNjZ3Ew8rxEKOc","cf73jxyN9Jt47QTJU6ziYh","d13zE+JplIfoNKUToR8M70","d3m7Sf4/BAOr9IyAdRa4xb","d8nvBMdbZLGbyb19edDkTT","da5ZIWSoFPoJJnI2xklOMO","ddnAYQ/R5P3LE/tXsFNm8I","e7ypVHaA5OZpapBDTd3IsA","e8Ueib+qJEhL6mXAHdnwbi","e8vIVo141Po5du1ZjZUXZ7","f28C6ukuFCoql5lQtRjYTJ","f7iWZGHv5FrZi3nobo/kXy","f869x5FmVJ/qhi+UAydO30","02delMVqdBD70a/HSD99FK","042bxh1G9Fyplo3aQCd1x6","08DzwCPqNHoJublJSrM1U8","2a2PheNZlFoq694lc2AZOG","36H02RWYlCG75YQKYPGAm0","3cCGVSHtNLXJcgbRXs203C","49vJ1k/3xBQrU4KlpPJOIR","5038oZybRGhYOd0sB56yln","57y69keEdMdpHGWsoh/U7H","58hM+xv3lJip/Gx1TEADsz","5aXoaL+w9FO4VGmGdvegih","5f/vFnlcVOgKkVAc8SVT/X","602an8oE1MyahHO2yRSn3N","61AV2VwzRPp7dIvaAKWWmq","61lCT3K8BDNae1kKbhzgaL","675ovJ2tVK2aLYfgPUWOMv","6fe2vruLFDoZ9S4DQtKCCU","79sdXMFK9HTLEFS4L6Ylyq","7aQFan4a5BmLg8gU+9B/ky","7dbCfMifZKv4tg420YyXHq","7fz2TdFghKOo++pvWSJx8x","83WAbEHIpFBpoT/z5yQ0Ph","87llVOFA9Fnr7OPQilZwvA","8855/VlrRKd6H0MSRnFxAU","890sB0tgJHoL3IakItcfiS","97mdHYCWJOoobFVVLwdaw6","9faAKrctJDVIXL3ZmAxRK7","9ftQ5KaURE+ILCZpPtkK1d","a4GoXHBC1NJrbaTp1DESEh","a9VOrzRZdGlbD290oAejCd","acidyfQJNBzLCUAGc3xAKe","b9EcOBbjdBAKWP9Trn8T2M","bdUCYSeoVIVpiq+So29yA/","c53PXllYJOBqyFPZC3MCt3","cameMuNT5F6pLXnQkeYPzw","cdwaNObXxJ35jRAHvPmnC8","d0JdysHmRIsayRfPyavmJB","d4FyAp+k1AI6T4bmPOYc2y","ea6fEZRaZK4bL3QvPLd473","ecpdLyjvZBwrvm+cedCcQy","ec9paK7p1AibCebaBvxFiC","f6VI7FcopEop+gqGsZhSec","fc1YAzHvFAFLNpssUFJ4O2"],"scenes":{"db://assets/Credit/CreditScene.fire":15,"db://assets/GameScene.fire":7,"db://assets/MainMenu/MainMenuScene.fire":43},"redirect":[50,0,89,0],"deps":["internal"],"packs":{"02ed9e8f2":[0,15,1,2,3],"0433330f0":[23,24,27],"05cae6757":[4,6,51,52,7,8,11,0,53,54,55,56,57,58,59,60,61,62,63,64,65,66,67,68,69,70,71,72,73,74,75,76,77,1,78,79,80,81,82,83,84,85,86,87,2,88,90,3,47,91,92],"061f5293d":[5,9,10,12,13,14,16,17,18,19,20,21,22,25,26,28,29,30,31,32,33,34,35,36,37,38,39,40,41,42,44,45,46,48,49],"0c7a10e82":[0,1,43,2,3]},"name":"main","importBase":"import","nativeBase":"native","debug":false,"isZip":false,"encrypted":false,"versions":{"import":["02ed9e8f2","bab5d","0433330f0","13083","05cae6757","e3230","061f5293d","04c40","0c7a10e82","8263f"],"native":[4,"16827",5,"e0e78",6,"18424",8,"94d53",9,"19730",10,"2d81a",11,"95ef2",12,"3f0c6",13,"0b634",14,"65425",16,"80549",17,"764f0",18,"c473b",19,"387f5",20,"86025",21,"c06a9",22,"c5c95",23,"4f0b8",24,"4260b",25,"7f96c",26,"2c7b9",27,"9ece5",28,"d1118",29,"165cb",30,"fb0e2",31,"cb021",32,"966e0",33,"8d37e",34,"83fcc",35,"8cc90",36,"cdb0c",37,"d4943",38,"a4b59",39,"c512c",40,"533df",41,"da443",42,"80a91",44,"b7c3d",45,"90cf4",46,"3659a",47,"859c5",48,"cc753",49,"65425"]}}